proml/__init__.py
proml/cli.py
proml/constraints.py
proml/formatter.py
proml/parser.py
proml/pipeline.py
proml/policy.py
proml/registry.py
proml/runtime.py
proml/adapters/__init__.py
proml/adapters/guidance_adapter.py
proml_cli-0.1.0.dist-info/licenses/LICENSE
proml_cli-0.1.0.dist-info/METADATA
proml_cli-0.1.0.dist-info/WHEEL
proml_cli-0.1.0.dist-info/entry_points.txt
proml_cli-0.1.0.dist-info/top_level.txt
proml_cli-0.1.0.dist-info/RECORD
