Metadata-Version: 2.4
Name: proml-cli
Version: 0.1.0
Summary: Prompt Markup Language toolkit for structured LLM workflows
Author: Johan Caripson
License: MIT
Project-URL: Homepage, https://github.com/Caripson/ProML
Project-URL: Documentation, https://github.com/Caripson/ProML/tree/main/docs
Project-URL: Source, https://github.com/Caripson/ProML
Requires-Python: >=3.10
License-File: LICENSE
Requires-Dist: ruamel.yaml>=0.18
Requires-Dist: PyYAML>=6.0
Provides-Extra: dev
Requires-Dist: mkdocs>=1.6; extra == "dev"
Requires-Dist: mkdocs-material>=9.5; extra == "dev"
Requires-Dist: pytest>=8.3; extra == "dev"
Requires-Dist: guidance>=0.1.0; extra == "dev"
Dynamic: license-file
